smev_transform/__init__.py
smev_transform/attribute.py
smev_transform/attribute_decoder.py
smev_transform/comparators.py
smev_transform/exceptions.py
smev_transform/text_decoder.py
smev_transform/transform.py
smev_transform/xml_namespace.py
smev_transform-2.0.0.dist-info/licenses/LICENSE
smev_transform-2.0.0.dist-info/METADATA
smev_transform-2.0.0.dist-info/WHEEL
smev_transform-2.0.0.dist-info/top_level.txt
smev_transform-2.0.0.dist-info/RECORD
