Metadata-Version: 2.4
Name: smev-transform
Version: 2.0.0
Summary: Реализация алгоритма трансформации urn://smev-gov-ru/xmldsig/transform для СМЭВ 3.5.0.27
Home-page: https://github.com/imdeniil/smev-transform
Author: Daniil
Author-email: Daniil <keemor821@gmail.com>
Maintainer-email: Daniil <keemor821@gmail.com>
License: MIT License
Project-URL: Homepage, https://github.com/imdeniil/smev-transform
Project-URL: Repository, https://github.com/imdeniil/smev-transform
Project-URL: Bug Reports, https://github.com/imdeniil/smev-transform/issues
Project-URL: Documentation, https://info.gosuslugi.ru/docs/section/%D0%A1%D0%9C%D0%AD%D0%92/%D0%9C%D0%B5%D1%82%D0%BE%D0%B4%D0%B8%D1%87%D0%B5%D1%81%D0%BA%D0%B8%D0%B5_%D0%B4%D0%BE%D0%BA%D1%83%D0%BC%D0%B5%D0%BD%D1%82%D1%8B/%D0%A1%D0%9C%D0%AD%D0%923/?id=758
Keywords: smev,смэв,xml,xmldsig,transformation,gosuslugi
Classifier: Development Status :: 5 - Production/Stable
Classifier: Intended Audience :: Developers
Classifier: Operating System :: OS Independent
Classifier: Programming Language :: Python :: 3
Classifier: Programming Language :: Python :: 3.7
Classifier: Programming Language :: Python :: 3.8
Classifier: Programming Language :: Python :: 3.9
Classifier: Programming Language :: Python :: 3.10
Classifier: Programming Language :: Python :: 3.11
Classifier: Programming Language :: Python :: 3.12
Classifier: Topic :: Text Processing :: Markup :: XML
Classifier: Topic :: Security :: Cryptography
Classifier: Topic :: Software Development :: Libraries :: Python Modules
Requires-Python: >=3.7
License-File: LICENSE
Provides-Extra: dev
Requires-Dist: pytest>=7.0.0; extra == "dev"
Requires-Dist: pytest-cov>=4.0.0; extra == "dev"
Dynamic: author
Dynamic: home-page
Dynamic: license-file
Dynamic: requires-python
